{
  "nodes": [
    {
      "standard_name": "Russian Mafia",
      "original_text_name": "Russian mafia",
      "aliases": [
        "Russian organized crime"
      ],
      "type": "mafia",
      "context": "General term for Russian organized crime groups; Ivankov was a prominent boss.",
      "time_period": "1990s-2000s"
    },
    {
      "standard_name": "Ivankov Gang",
      "original_text_name": "Ivankov's gang",
      "aliases": [
        "Yaponchik's gang"
      ],
      "type": "gang",
      "context": "Ivankov's criminal group operating in Moscow and later in Brighton Beach, Brooklyn.",
      "time_period": "1970s-2009"
    },
    {
      "standard_name": "Cosa Nostra",
      "original_text_name": "Cosa Nostra",
      "aliases": [],
      "type": "mafia",
      "context": "Italian-American Mafia; mentioned for contrast with Ivankov's methods.",
      "time_period": null
    },
    {
      "standard_name": "Dagestani Bratva",
      "original_text_name": "Dagestani Bratva",
      "aliases": [],
      "type": "mafia",
      "context": "Criminal group from Dagestan; sent a tribute to Ivankov's funeral.",
      "time_period": null
    },
    {
      "standard_name": "Kazakh Bratva",
      "original_text_name": "Kazakh Bratva",
      "aliases": [],
      "type": "mafia",
      "context": "Criminal group from Kazakhstan; sent a tribute to Ivankov's funeral.",
      "time_period": null
    },
    {
      "standard_name": "Usoyan Clan",
      "original_text_name": "Aslan Usoyan (Ded Khasan)",
      "aliases": [
        "Ded Khasan",
        "Grandpa Hassan"
      ],
      "type": "clan",
      "context": "Crime group led by Aslan Usoyan; Ivankov sided with them in a gang war.",
      "time_period": "1990s-2013"
    },
    {
      "standard_name": "Oniani Clan",
      "original_text_name": "Tariel Oniani",
      "aliases": [],
      "type": "clan",
      "context": "Georgian crime group led by Tariel Oniani; rival of Usoyan.",
      "time_period": "1990s-2010s"
    },
    {
      "standard_name": "Brothers' Circle",
      "original_text_name": "Brothers' Circle",
      "aliases": [],
      "type": "other",
      "context": "International criminal network; Lasha Shushanashvili is a member.",
      "time_period": null
    },
    {
      "standard_name": "Mazutka Gang",
      "original_text_name": "Mazutka gang",
      "aliases": [
        "Mazutkinskaya OPG"
      ],
      "type": "gang",
      "context": "Russian gang headed by Alexei Petrov; operated in Israel, Germany, Austria.",
      "time_period": "1990s-2019"
    },
    {
      "standard_name": "Solntsevskaya Bratva",
      "original_text_name": "Mikhas's Solntsevskaya",
      "aliases": [
        "Solntsevskaya"
      ],
      "type": "mafia",
      "context": "Powerful Russian mafia group; gained Ivankov's assets after his death.",
      "time_period": "1980s-present"
    },
    {
      "standard_name": "Mogilevich Crime Network",
      "original_text_name": "Semion Mogilevich crime network",
      "aliases": [],
      "type": "mafia",
      "context": "Criminal network led by Semion Mogilevich; gained Ivankov's assets after his death.",
      "time_period": "1990s-present"
    }
  ],
  "edges": [
    {
      "source": "Ivankov Gang",
      "target": "Russian Mafia",
      "relationship": "alliance",
      "detail": null,
      "context": "Ivankov was a Russian mafia boss; his gang was part of the broader Russian mafia.",
      "time_period": "1970s-2009"
    },
    {
      "source": "Ivankov Gang",
      "target": "Usoyan Clan",
      "relationship": "alliance",
      "detail": null,
      "context": "Ivankov sided with Usoyan in a gang war against Oniani.",
      "time_period": "2009"
    },
    {
      "source": "Usoyan Clan",
      "target": "Oniani Clan",
      "relationship": "rivalry",
      "detail": null,
      "context": "Ongoing gang war between Usoyan and Oniani; Ivankov's murder was part of it.",
      "time_period": "2000s-2010s"
    },
    {
      "source": "Ivankov Gang",
      "target": "Mazutka Gang",
      "relationship": "alliance",
      "detail": null,
      "context": "Alexei Petrov, successor to Ivankov, headed the Mazutka gang.",
      "time_period": "1992-2009"
    },
    {
      "source": "Mazutka Gang",
      "target": "Ivankov Gang",
      "relationship": "alliance",
      "detail": null,
      "context": "Petrov headed Ivankov's affairs in Moscow and Europe after Ivankov left for the US.",
      "time_period": "1992-2009"
    },
    {
      "source": "Solntsevskaya Bratva",
      "target": "Ivankov Gang",
      "relationship": "rivalry",
      "detail": null,
      "context": "Solntsevskaya gained Ivankov's criminal assets after his death.",
      "time_period": "2009"
    },
    {
      "source": "Mogilevich Crime Network",
      "target": "Ivankov Gang",
      "relationship": "rivalry",
      "detail": null,
      "context": "Mogilevich's network gained Ivankov's criminal assets after his death.",
      "time_period": "2009"
    },
    {
      "source": "Mogilevich Crime Network",
      "target": "Ivankov Gang",
      "relationship": "alliance",
      "detail": null,
      "context": "Ivankov's son represented his father's interests at meetings with Mogilevich, indicating closeness.",
      "time_period": "1990s-2009"
    },
    {
      "source": "Brothers' Circle",
      "target": "Usoyan Clan",
      "relationship": "alliance",
      "detail": null,
      "context": "Lasha Shushanashvili, a member of Brothers' Circle, is close to Usoyan.",
      "time_period": null
    }
  ],
  "source_file": "Vyacheslav_Ivankov"
}