{
  "nodes": [
    {
      "standard_name": "Manitoba Warriors",
      "original_text_name": "Manitoba Warriors",
      "aliases": [
        "MW"
      ],
      "type": "gang",
      "context": "Indigenous street gang based in Winnipeg, Manitoba, Canada, involved in drug trafficking, auto theft, and other crimes.",
      "time_period": "1992-present"
    },
    {
      "standard_name": "Indian Posse",
      "original_text_name": "Indian Posse",
      "aliases": [],
      "type": "gang",
      "context": "Indigenous street gang, rival of the Manitoba Warriors, based in Winnipeg.",
      "time_period": "1990s-present"
    },
    {
      "standard_name": "Hells Angels",
      "original_text_name": "Hells Angels",
      "aliases": [],
      "type": "motorcycle_club",
      "context": "Outlaw motorcycle gang; Manitoba Warriors support and facilitate criminal activities for them.",
      "time_period": "1948-present"
    },
    {
      "standard_name": "Overlords",
      "original_text_name": "Overlords",
      "aliases": [],
      "type": "gang",
      "context": "Gang that was absorbed into the Manitoba Warriors.",
      "time_period": "1990s"
    },
    {
      "standard_name": "Los Bravos",
      "original_text_name": "los Bravos",
      "aliases": [
        "los Bravos biker gang"
      ],
      "type": "motorcycle_club",
      "context": "Biker gang that allied with Manitoba Warriors and later joined Hells Angels.",
      "time_period": "1990s-2000"
    },
    {
      "standard_name": "Native Syndicate",
      "original_text_name": "Native Syndicate",
      "aliases": [],
      "type": "gang",
      "context": "Rival gang to Manitoba Warriors.",
      "time_period": "1990s-present"
    },
    {
      "standard_name": "Bloods",
      "original_text_name": "Bloods sets",
      "aliases": [
        "Bloods"
      ],
      "type": "gang",
      "context": "Rival gang to Manitoba Warriors in Winnipeg.",
      "time_period": "2000s-present"
    },
    {
      "standard_name": "Madcowz",
      "original_text_name": "Madcowz",
      "aliases": [],
      "type": "gang",
      "context": "Afro-Canadian-based gang, rival to Manitoba Warriors.",
      "time_period": "2000s-present"
    },
    {
      "standard_name": "Most Organized Brothers",
      "original_text_name": "Most Organized Brothers",
      "aliases": [
        "MOB"
      ],
      "type": "gang",
      "context": "Formerly affiliated with Manitoba Warriors, later fell out.",
      "time_period": "2000s"
    },
    {
      "standard_name": "Saskatchewan Warriors",
      "original_text_name": "Saskatchewan Warriors",
      "aliases": [
        "SW"
      ],
      "type": "gang",
      "context": "Aboriginal street gang active in Saskatchewan, originally under Manitoba Warriors banner.",
      "time_period": "1990s-present"
    },
    {
      "standard_name": "Alberta Warriors",
      "original_text_name": "Alberta Warriors",
      "aliases": [
        "AW"
      ],
      "type": "gang",
      "context": "Aboriginal street gang active in Alberta, originally under Manitoba Warriors banner.",
      "time_period": "1990s-present"
    },
    {
      "standard_name": "CENTRAL",
      "original_text_name": "CENTRAL",
      "aliases": [],
      "type": "gang",
      "context": "Affiliated with Manitoba Warriors.",
      "time_period": null
    },
    {
      "standard_name": "Loyalty Honour Silence",
      "original_text_name": "Loyalty Honour Silence",
      "aliases": [],
      "type": "gang",
      "context": "Affiliated with Manitoba Warriors.",
      "time_period": null
    },
    {
      "standard_name": "MOB Squad",
      "original_text_name": "MOB Squad",
      "aliases": [],
      "type": "gang",
      "context": "Affiliated with Manitoba Warriors.",
      "time_period": null
    },
    {
      "standard_name": "Ruthless Warriors",
      "original_text_name": "Ruthless Warriors",
      "aliases": [],
      "type": "faction",
      "context": "Former cell of Manitoba Warriors.",
      "time_period": "late 1990s"
    },
    {
      "standard_name": "Central Warriors",
      "original_text_name": "Central Warriors",
      "aliases": [],
      "type": "faction",
      "context": "Former cell of Manitoba Warriors.",
      "time_period": "late 1990s"
    }
  ],
  "edges": [
    {
      "source": "Manitoba Warriors",
      "target": "Indian Posse",
      "relationship": "rivalry",
      "detail": null,
      "context": "Manitoba Warriors were established to rival Indian Posse; they have a violent rivalry.",
      "time_period": "1993-present"
    },
    {
      "source": "Manitoba Warriors",
      "target": "Hells Angels",
      "relationship": "alliance",
      "detail": null,
      "context": "Manitoba Warriors support and facilitate criminal activities for Hells Angels; junior partners.",
      "time_period": "2000-present"
    },
    {
      "source": "Manitoba Warriors",
      "target": "Overlords",
      "relationship": "alliance",
      "detail": null,
      "context": "Manitoba Warriors absorbed the Overlords gang into their ranks.",
      "time_period": "1990s"
    },
    {
      "source": "Manitoba Warriors",
      "target": "Los Bravos",
      "relationship": "alliance",
      "detail": null,
      "context": "Manitoba Warriors formed an alliance with los Bravos biker gang and purchased drugs from them.",
      "time_period": "1990s-2000"
    },
    {
      "source": "Manitoba Warriors",
      "target": "Native Syndicate",
      "relationship": "rivalry",
      "detail": null,
      "context": "Long-time rivalry with Native Syndicate since early-to-mid 1990s.",
      "time_period": "1990s-present"
    },
    {
      "source": "Manitoba Warriors",
      "target": "Bloods",
      "relationship": "rivalry",
      "detail": null,
      "context": "Rivalry with Bloods sets in Winnipeg's North-End and West Central neighborhoods.",
      "time_period": "2000s-present"
    },
    {
      "source": "Manitoba Warriors",
      "target": "Madcowz",
      "relationship": "rivalry",
      "detail": null,
      "context": "Rivalry with Madcowz gang in Winnipeg.",
      "time_period": "2000s-present"
    },
    {
      "source": "Manitoba Warriors",
      "target": "Most Organized Brothers",
      "relationship": "rivalry",
      "detail": null,
      "context": "Formerly affiliated, but alliance fell apart leading to tension and bad blood.",
      "time_period": "2000s"
    },
    {
      "source": "Manitoba Warriors",
      "target": "Saskatchewan Warriors",
      "relationship": "alliance",
      "detail": null,
      "context": "Saskatchewan Warriors originally worked for Manitoba Warriors; now separate but affiliated.",
      "time_period": "1990s-present"
    },
    {
      "source": "Manitoba Warriors",
      "target": "Alberta Warriors",
      "relationship": "alliance",
      "detail": null,
      "context": "Alberta Warriors adopted the Warriors banner under Manitoba Warriors; now separate but work together.",
      "time_period": "1990s-present"
    },
    {
      "source": "Manitoba Warriors",
      "target": "CENTRAL",
      "relationship": "alliance",
      "detail": null,
      "context": "CENTRAL is an affiliated organization.",
      "time_period": null
    },
    {
      "source": "Manitoba Warriors",
      "target": "Loyalty Honour Silence",
      "relationship": "alliance",
      "detail": null,
      "context": "Loyalty Honour Silence is an affiliated organization.",
      "time_period": null
    },
    {
      "source": "Manitoba Warriors",
      "target": "MOB Squad",
      "relationship": "alliance",
      "detail": null,
      "context": "MOB Squad is an affiliated organization.",
      "time_period": null
    },
    {
      "source": "Ruthless Warriors",
      "target": "Manitoba Warriors",
      "relationship": "alliance",
      "detail": null,
      "context": "Ruthless Warriors was a cell of Manitoba Warriors.",
      "time_period": "late 1990s"
    },
    {
      "source": "Central Warriors",
      "target": "Manitoba Warriors",
      "relationship": "alliance",
      "detail": null,
      "context": "Central Warriors was a cell of Manitoba Warriors.",
      "time_period": "late 1990s"
    }
  ],
  "source_file": "Manitoba_Warriors"
}