{
  "nodes": [
    {
      "standard_name": "Sinaloa Cartel",
      "original_text_name": "Sinaloa drug cartel",
      "aliases": [
        "Sinaloa Cartel"
      ],
      "type": "cartel",
      "context": "Drug trafficking cartel operating in Sinaloa, Mexico, targeted by government forces.",
      "time_period": null
    },
    {
      "standard_name": "Rurales",
      "original_text_name": "Rurales",
      "aliases": [
        "Cuerpo de Defensa Rural",
        "Rural Defense Corps"
      ],
      "type": "militia",
      "context": "Part-time militia force used by Mexican government against drug cartels.",
      "time_period": "1913-present"
    }
  ],
  "edges": [],
  "source_file": "Mexican_Army"
}